pyhubctl/__init__.py
pyhubctl/pyhubctl.py
pyhubctl-1.0.0.dist-info/LICENSE.txt
pyhubctl-1.0.0.dist-info/METADATA
pyhubctl-1.0.0.dist-info/WHEEL
pyhubctl-1.0.0.dist-info/top_level.txt
pyhubctl-1.0.0.dist-info/RECORD
