Metadata-Version: 2.1
Name: pyhubctl
Version: 1.0.0
Summary: Python wrapper for the uhubctl project.
Home-page: https://github.com/DuraTech-Industries/pyhubctl.git
Author: Dakota Horstman
Author-email: dakota.horstman@duratech.com
License: MIT
Project-URL: Documentation, https://pyscaffold.org/
Platform: any
Classifier: Development Status :: 4 - Beta
Classifier: Programming Language :: Python
License-File: LICENSE.txt
Requires-Dist: importlib-metadata ; python_version < "3.8"
Provides-Extra: testing
Requires-Dist: setuptools ; extra == 'testing'
Requires-Dist: pytest ; extra == 'testing'
Requires-Dist: pytest-cov ; extra == 'testing'
